cdis_pipe_utils/__init__.py
cdis_pipe_utils/df_util.py
cdis_pipe_utils/fastq_util.py
cdis_pipe_utils/pipe_util.py
cdis_pipe_utils/postgres.py
cdis_pipe_utils/time_util.py
cdis_pipe_utils-0.23.dist-info/DESCRIPTION.rst
cdis_pipe_utils-0.23.dist-info/METADATA
cdis_pipe_utils-0.23.dist-info/RECORD
cdis_pipe_utils-0.23.dist-info/WHEEL
cdis_pipe_utils-0.23.dist-info/metadata.json
cdis_pipe_utils-0.23.dist-info/top_level.txt
