Metadata-Version: 2.0
Name: cdis-pipe-utils
Version: 0.23
Summary: Reusable code to call pipeline tools and get time/mem metrics
Home-page: https://github.com/LabAdvComp/cdis_pipe_utils
Author: Jeremiah H. Savage
Author-email: jeremiahsavage@gmail.com
License: Apache 2.0
Platform: UNKNOWN
Classifier: Development Status :: 3 - Alpha
Classifier: Intended Audience :: Developers
Classifier: License :: OSI Approved :: Apache Software License
Classifier: Programming Language :: Python
Classifier: Programming Language :: Python :: 2
Classifier: Programming Language :: Python :: 3
Classifier: Topic :: Software Development :: Libraries
Requires-Dist: pandas
Requires-Dist: psycopg2 (>=2.6.1)
Requires-Dist: sqlalchemy
